genai/__init__.py
genai/models/__init__.py
tests/__init__.py
genai_sdk-0.0.1.dist-info/LICENSE
genai_sdk-0.0.1.dist-info/METADATA
genai_sdk-0.0.1.dist-info/WHEEL
genai_sdk-0.0.1.dist-info/top_level.txt
genai_sdk-0.0.1.dist-info/RECORD
