Metadata-Version: 2.1
Name: genai-sdk
Version: 0.0.1
Summary: SDK de conexão com o mobileX GenAI
Home-page: https://github.com/mobilex-neo/genai-sdk
Author: Luiz Carvalho
Author-email: dev@mtmtecnologia.com.br
Classifier: Programming Language :: Python :: 3
Classifier: License :: OSI Approved :: MIT License
Classifier: Operating System :: OS Independent
Requires-Python: >=3.11
License-File: LICENSE
Requires-Dist: requests >=2.26.0
